steamship/__init__.py
steamship/agents/__init__.py
steamship/agents/basic_chat.py
steamship/agents/functions_based.py
steamship/agents/logging.py
steamship/agents/utils.py
steamship/agents/examples/__init__.py
steamship/agents/examples/chatgpt_api.py
steamship/agents/examples/chatgpt_with_web_and_telegram.py
steamship/agents/examples/document_qa_agent.py
steamship/agents/examples/example_assistant.py
steamship/agents/examples/example_assistant_with_caching.py
steamship/agents/examples/example_react_assistant.py
steamship/agents/examples/fact_learner.py
steamship/agents/examples/telegram_bot.py
steamship/agents/functional/__init__.py
steamship/agents/functional/functions_based.py
steamship/agents/functional/output_parser.py
steamship/agents/llms/__init__.py
steamship/agents/llms/openai.py
steamship/agents/llms/steamship_llm.py
steamship/agents/mixins/__init__.py
steamship/agents/mixins/transports/__init__.py
steamship/agents/mixins/transports/slack.py
steamship/agents/mixins/transports/steamship_widget.py
steamship/agents/mixins/transports/telegram.py
steamship/agents/mixins/transports/transport.py
steamship/agents/react/__init__.py
steamship/agents/react/output_parser.py
steamship/agents/react/react.py
steamship/agents/schema/__init__.py
steamship/agents/schema/action.py
steamship/agents/schema/agent.py
steamship/agents/schema/cache.py
steamship/agents/schema/chathistory.py
steamship/agents/schema/context.py
steamship/agents/schema/functions.py
steamship/agents/schema/llm.py
steamship/agents/schema/message_selectors.py
steamship/agents/schema/output_parser.py
steamship/agents/schema/text_splitters.py
steamship/agents/schema/tool.py
steamship/agents/service/__init__.py
steamship/agents/service/agent_service.py
steamship/agents/tools/__init__.py
steamship/agents/tools/base_tools.py
steamship/agents/tools/audio_transcription/__init__.py
steamship/agents/tools/audio_transcription/assembly_speech_to_text_tool.py
steamship-2.17.34.dist-info/AUTHORS.rst
steamship-2.17.34.dist-info/LICENSE
steamship-2.17.34.dist-info/METADATA
steamship-2.17.34.dist-info/WHEEL
steamship-2.17.34.dist-info/entry_points.txt
steamship-2.17.34.dist-info/top_level.txt
steamship-2.17.34.dist-info/RECORD
