Metadata-Version: 2.1
Name: steamship
Version: 2.17.34
Summary: The fastest way to add language AI to your product.
License-File: LICENSE
License-File: AUTHORS.rst
Requires-Dist: requests~=2.28.1
Requires-Dist: pydantic~=1.10.2
Requires-Dist: aiohttp~=3.8.4
Requires-Dist: inflection~=0.5.1
Requires-Dist: fluent-logger~=0.10.0
Requires-Dist: toml~=0.10.2
Requires-Dist: click~=8.1.3
Requires-Dist: semver~=3.0.0
Requires-Dist: tiktoken~=0.4.0
